comed/__init__.py
comed/agents.py
comed/analysis.py
comed/core.py
comed/cot.py
comed/io.py
comed/rag.py
comed/report.py
comed/risk.py
comed/search.py
comed/utils.py
comed-2.1.6.dist-info/LICENSE
comed-2.1.6.dist-info/METADATA
comed-2.1.6.dist-info/WHEEL
comed-2.1.6.dist-info/top_level.txt
comed-2.1.6.dist-info/RECORD
